glam/__init__.py
glam/_lib.py
theglam-1.2.1.dist-info/METADATA
theglam-1.2.1.dist-info/WHEEL
theglam-1.2.1.dist-info/top_level.txt
theglam-1.2.1.dist-info/RECORD
